marksplitz/__init__.py
marksplitz/marksplitz.py
marksplitz-0.1.dev12.dist-info/LICENSE.txt
marksplitz-0.1.dev12.dist-info/METADATA
marksplitz-0.1.dev12.dist-info/WHEEL
marksplitz-0.1.dev12.dist-info/entry_points.txt
marksplitz-0.1.dev12.dist-info/top_level.txt
marksplitz-0.1.dev12.dist-info/RECORD
