Metadata-Version: 2.1
Name: marksplitz
Version: 0.1.dev12
Summary: Command-line utility to split a Markdown file into linked static web pages.
Author-email: Bill Melvin <bill@billmelvin.com>
License: MIT License
Keywords: markdown,converter,html,slideshow
Requires-Python: >=3.8
License-File: LICENSE.txt
Requires-Dist: mistune
